README.md
setup.py
pulumi_ct/__init__.py
pulumi_ct/_utilities.py
pulumi_ct/ct_config.py
pulumi_ct/provider.py
pulumi_ct/pulumi-plugin.json
pulumi_ct/py.typed
pulumi_ct.egg-info/PKG-INFO
pulumi_ct.egg-info/SOURCES.txt
pulumi_ct.egg-info/dependency_links.txt
pulumi_ct.egg-info/not-zip-safe
pulumi_ct.egg-info/requires.txt
pulumi_ct.egg-info/top_level.txt