Metadata-Version: 2.1
Name: pulumi-ct
Version: 0.0.1a1652206837
Summary: A Pulumi package for creating and managing ct cloud resources.
Home-page: https://www.cuemby.com
License: Apache-2.0
Project-URL: Repository, https://github.com/cuemby/pulumi-ct
Keywords: cuemby ct category/cloud
Platform: UNKNOWN
